nuctools/__init__.py
nuctools/_version.py
nuctools/agl_tools.py
nuctools/ags_tools.py
nuctools/ampx_tools.py
nuctools/chem_tools.py
nuctools/endf_tools.py
nuctools/funky.py
nuctools/hdf5_tools.py
nuctools/level_density.py
nuctools/math_tools.py
nuctools/mcnp_tools.py
nuctools/physics_tools.py
nuctools/plot_tools.py
nuctools/rpixdr_tools.py
nuctools/sam_tools.py
nuctools/sample_create.py
nuctools/scaledata_tools.py
nuctools/tof_tools.py
nuctools/trans_tools.py
nuctools/triton_tools.py
nuctools/urr_tools.py
nuctools/venus_tools.py
nuctools/data/README.md
nuctools/data/mm-dict.json
nuctools/data/protons.json
nuctools/data/unary-list.json
nuctools-1.13.0.dist-info/licenses/LICENSE.md
nuctools-1.13.0.dist-info/METADATA
nuctools-1.13.0.dist-info/WHEEL
nuctools-1.13.0.dist-info/top_level.txt
nuctools-1.13.0.dist-info/RECORD
