Metadata-Version: 2.4
Name: nuctools
Version: 1.13.0
Summary: nuclear data reduction tools
Home-page: https://github.com/brownjm1968/nuctools
Author: Jesse Brown
Author-email: brownjm1968@gmail.com
License: BSD 3-clause
Classifier: Programming Language :: Python :: 3
Classifier: Operating System :: Unix
Classifier: Operating System :: MacOS :: MacOS X
Classifier: Operating System :: Microsoft :: Windows
License-File: LICENSE.md
Requires-Dist: numpy
Requires-Dist: pandas
Requires-Dist: scipy
Requires-Dist: h5py
Requires-Dist: pyyaml
Requires-Dist: matplotlib
Requires-Dist: pytest
Requires-Dist: tifffile
Dynamic: author
Dynamic: author-email
Dynamic: classifier
Dynamic: description
Dynamic: description-content-type
Dynamic: home-page
Dynamic: license
Dynamic: license-file
Dynamic: requires-dist
Dynamic: summary
